minicurve/__init__.py
minicurve/curve.py
minicurve/helpers.py
minicurve/modsqrt.py
minicurve/visualization.py
minicurve-0.1.0.dist-info/LICENSE
minicurve-0.1.0.dist-info/METADATA
minicurve-0.1.0.dist-info/WHEEL
minicurve-0.1.0.dist-info/top_level.txt
minicurve-0.1.0.dist-info/RECORD
