Metadata-Version: 2.1
Name: minicurve
Version: 0.1.0
Summary: Small, insecure and visual ECC library for educational purposes
Home-page: https://github.com/marekyggdrasil/potatoes
Author: Marek Narozniak
Author-email: marek.yggdrasil@gmail.com
License: MIT
Platform: UNKNOWN
Classifier: Programming Language :: Python :: 3
Classifier: Programming Language :: Python :: 2
Classifier: License :: OSI Approved :: MIT License
Classifier: Operating System :: OS Independent
License-File: LICENSE
Requires-Dist: numpy
Requires-Dist: matplotlib
